bdbcontrib/__init__.py
bdbcontrib/bql_utils.py
bdbcontrib/crosscat_utils.py
bdbcontrib/diagnostic_utils.py
bdbcontrib/loggers.py
bdbcontrib/parallel.py
bdbcontrib/plot_utils.py
bdbcontrib/population.py
bdbcontrib/population_method.py
bdbcontrib/py_utils.py
bdbcontrib/recipes.py
bdbcontrib/shell_utils.py
bdbcontrib/verify_notebook.py
bdbcontrib/version.py
bdbcontrib/experiments/__init__.py
bdbcontrib/experiments/probe.py
bdbcontrib/experiments/visualization.py
bdbcontrib/metamodels/__init__.py
bdbcontrib/metamodels/composer.py
bdbcontrib/predictors/__init__.py
bdbcontrib/predictors/keplers_law.py
bdbcontrib/predictors/multiple_regression.py
bdbcontrib/predictors/predictor.py
bdbcontrib/predictors/random_forest.py
bdbcontrib/predictors/sklearn_utils.py
bdbcontrib-0.1.8.1.data/data/bdbcontrib/examples/Index.ipynb
bdbcontrib-0.1.8.1.data/data/bdbcontrib/examples/on-stability-testing.md
bdbcontrib-0.1.8.1.data/data/bdbcontrib/examples/ma-school-districts/ma-school-districts.csv
bdbcontrib-0.1.8.1.data/data/bdbcontrib/examples/ma-school-districts/ma_schools.py
bdbcontrib-0.1.8.1.data/data/bdbcontrib/examples/ma-school-districts/MASchoolDistricts.ipynb
bdbcontrib-0.1.8.1.data/data/bdbcontrib/examples/satellites/build_bdbs.py
bdbcontrib-0.1.8.1.data/data/bdbcontrib/examples/satellites/probe.py
bdbcontrib-0.1.8.1.data/data/bdbcontrib/examples/satellites/querying-and-plotting.ipynb
bdbcontrib-0.1.8.1.data/data/bdbcontrib/examples/satellites/satellites.bql
bdbcontrib-0.1.8.1.data/data/bdbcontrib/examples/satellites/satellites.csv
bdbcontrib-0.1.8.1.data/data/bdbcontrib/examples/satellites/Satellites.ipynb
bdbcontrib-0.1.8.1.data/data/bdbcontrib/examples/satellites/satellites_codebook.csv
bdbcontrib-0.1.8.1.data/data/bdbcontrib/examples/satellites/visualize.py
bdbcontrib-0.1.8.1.data/scripts/bayesdb-demo
bdbcontrib-0.1.8.1.dist-info/DESCRIPTION.rst
bdbcontrib-0.1.8.1.dist-info/METADATA
bdbcontrib-0.1.8.1.dist-info/metadata.json
bdbcontrib-0.1.8.1.dist-info/RECORD
bdbcontrib-0.1.8.1.dist-info/top_level.txt
bdbcontrib-0.1.8.1.dist-info/WHEEL
