Metadata-Version: 2.0
Name: bdbcontrib
Version: 0.1.8.1
Summary: Hodgepodge library of extras for bayeslite
Home-page: http://probcomp.csail.mit.edu/bayesdb
Author: MIT Probabilistic Computing Project
Author-email: bayesdb@mit.edu
License: Apache License, Version 2.0
Platform: UNKNOWN
Requires-Dist: bayeslite (>=0.1.8)
Requires-Dist: ipython[notebook] (>=3)
Requires-Dist: markdown2
Requires-Dist: matplotlib
Requires-Dist: numpy
Requires-Dist: numpydoc
Requires-Dist: pandas (>=0.17.0)
Requires-Dist: seaborn (>=0.7)
Requires-Dist: scipy
Requires-Dist: sklearn
Requires-Dist: sklearn-pandas
Requires-Dist: sphinx
Requires-Dist: tornado (>=4.0)
